physiology_analysis_tools/__init__.py
physiology_analysis_tools/ecg_analysis_tool.ui
physiology_analysis_tools/main.py
physiology_analysis_tools/examples/10 long.txt
physiology_analysis_tools/examples/10.txt
physiology_analysis_tools/examples/57 long.txt
physiology_analysis_tools/examples/57.txt
physiology_analysis_tools/examples/9 long.txt
physiology_analysis_tools/examples/9.txt
physiology_analysis_tools/examples/M00430943.adicht
physiology_analysis_tools/examples/M00441108.adicht
physiology_analysis_tools/examples/M00445321.adicht
physiology_analysis_tools/modules/__init__.py
physiology_analysis_tools/modules/arrhythmia_detection.py
physiology_analysis_tools/modules/heartbeat_detection.py
physiology_analysis_tools/modules/ml_tools.py
physiology_analysis_tools/modules/signal_converters/__init__.py
physiology_analysis_tools/modules/signal_converters/adi_extract.py
physiology_analysis_tools/modules/signal_converters/dsi_fp_matlab_extract.py
physiology_analysis_tools/modules/signal_converters/edf_extract.py
physiology_analysis_tools/modules/signal_converters/labchart_text_extract.py
physiology_analysis_tools/modules/signal_converters/pcc_extract.py
physiology_analysis_tools/modules/signal_converters/pklgzip_extract.py
physiology_analysis_tools/modules/signal_converters/signal_filters_and_analyzers.py
physiology_analysis_tools-0.0.19.dist-info/METADATA
physiology_analysis_tools-0.0.19.dist-info/WHEEL
physiology_analysis_tools-0.0.19.dist-info/licenses/LICENSE
physiology_analysis_tools-0.0.19.dist-info/RECORD
