Metadata-Version: 2.3
Name: physiology_analysis_tools
Version: 0.0.19
Project-URL: Repository, https://github.com/realchrisward/Physiology-Analysis-Tools
Maintainer-email: Chris Ward <ward.chris.s@gmail.com>
License:                     GNU GENERAL PUBLIC LICENSE
License-File: LICENSE
Keywords: arrhythmia,ecg
Classifier: Development Status :: 3 - Alpha
Classifier: Programming Language :: Python
Requires-Python: >=3.12
Requires-Dist: adi-reader>=0.0.13
Requires-Dist: numpy>=2.2.2
Requires-Dist: pandas>=2.2.3
Requires-Dist: pyqtgraph>=0.13.7
Requires-Dist: pyside6==6.8.2
Requires-Dist: scikit-learn>=1.6.1
Requires-Dist: scipy>=1.15.1
Requires-Dist: xlsxwriter>=3.2.2
